prod_assert/__init__.py
prod_assert/_main.py
prod_assert-1.0.0.dist-info/licenses/LICENSE
prod_assert-1.0.0.dist-info/WHEEL
prod_assert-1.0.0.dist-info/METADATA
prod_assert-1.0.0.dist-info/RECORD
