Metadata-Version: 2.4
Name: prod-assert
Version: 1.0.0
Summary: Prod safe Python assert library
Keywords: assert,asserts,prod
Author: Ivan Derdić
Author-email: Ivan Derdić <ivan.derdic@proton.me>
License-Expression: Apache-2.0
License-File: LICENSE
Requires-Dist: uv-build>=0.9.17
Requires-Python: >=3.9
Project-URL: Homepage, https://github.com/IvanDerdicDer/prod_assert
